fw_gear_file_metadata_importer/P15E_private_tags.csv
fw_gear_file_metadata_importer/__init__.py
fw_gear_file_metadata_importer/derived.py
fw_gear_file_metadata_importer/geometry.py
fw_gear_file_metadata_importer/main.py
fw_gear_file_metadata_importer/parser.py
fw_gear_file_metadata_importer/transform.py
fw_gear_file_metadata_importer/util.py
fw_gear_file_metadata_importer/files/bruker.py
fw_gear_file_metadata_importer/files/dicom.py
fw_gear_file_metadata_importer/files/eeg.py
fw_gear_file_metadata_importer/files/ge.py
fw_gear_file_metadata_importer/files/nifti.py
fw_gear_file_metadata_importer/files/philips.py
fw_gear_file_metadata_importer/files/siemens.py
fw_gear_file_metadata_importer/files/video.py
fw_gear_file_metadata_importer-1.7.2.dist-info/METADATA
fw_gear_file_metadata_importer-1.7.2.dist-info/WHEEL
fw_gear_file_metadata_importer-1.7.2.dist-info/licenses/LICENSE
fw_gear_file_metadata_importer-1.7.2.dist-info/RECORD
