Metadata-Version: 2.4
Name: fw-gear-file-metadata-importer
Version: 1.7.2
Summary: Extract metadata of input file to Flywheel.
Author-email: Flywheel <support@flywheel.io>
License-Expression: MIT
License-File: LICENSE
Requires-Python: ~=3.11
Requires-Dist: ffmpegio<0.12.0,>=0.11.1
Requires-Dist: flywheel-sdk<19,>=18
Requires-Dist: fw-file>=4.2.0
Requires-Dist: fw-gear>=0.3.0
Requires-Dist: mne<1.8,>=1.5.1
Requires-Dist: nibabel~=5.2
Requires-Dist: pytz~=2021.3
Requires-Dist: ruamel-yaml<0.17,>=0.16
